<Properties StartupConfiguration="{7307386A-5C43-484F-A1CC-003D2AF6D15D}|Default">
  <MonoDevelop.Ide.DebuggingService.PinnedWatches />
  <MonoDevelop.Ide.DebuggingService.Breakpoints>
    <BreakpointStore />
  </MonoDevelop.Ide.DebuggingService.Breakpoints>
  <MonoDevelop.Ide.Workspace ActiveConfiguration="Debug" />
  <MonoDevelop.Ide.Workbench ActiveDocument="Models/UserDto.cs">
    <Files>
      <File FileName="Models/User.cs" Line="7" Column="14" />
      <File FileName="DAO/UserDao.cs" Line="49" Column="28" />
      <File FileName="Interfaces/IUserService.cs" Line="9" Column="19" />
      <File FileName="Models/UserDto.cs" Line="11" Column="15" />
    </Files>
    <Pads>
      <Pad Id="ProjectPad">
        <State name="__root__">
          <Node name="07232024_s6_progetto">
            <Node name="07232024_s6_progetto" selected="True">
              <Node name="DAO" expanded="True" />
              <Node name="Interfaces" expanded="True" />
              <Node name="Models" expanded="True" />
              <Node name="Services" expanded="True" />
              <Node name="Views" expanded="True">
                <Node name="Reservations" expanded="True" />
              </Node>
            </Node>
          </Node>
        </State>
      </Pad>
    </Pads>
  </MonoDevelop.Ide.Workbench>
  <MultiItemStartupConfigurations />
  <MonoDevelop.Ide.ItemProperties.07232024__s6__progetto PreferredExecutionTarget="/Applications/Google Chrome.app" />
</Properties>